README.md
requirements.txt
setup.py
sprintstats
wikifysprint
lib/__init__.py
lib/configuration.py
lib/confluence.py
lib/jirahelpers.py
lib/output.py
pd_sprintstats.egg-info/PKG-INFO
pd_sprintstats.egg-info/SOURCES.txt
pd_sprintstats.egg-info/dependency_links.txt
pd_sprintstats.egg-info/requires.txt
pd_sprintstats.egg-info/top_level.txt
templates/__init__.py
templates/__init__.pyc
templates/sprint-review.html.j2