Metadata-Version: 1.0
Name: pd-sprintstats
Version: 3.2.2
Summary: Gathers some statistics for a sprint from JIRA
Home-page: UNKNOWN
Author: Jason Diller
Author-email: jdiller@pagerduty.com
License: UNKNOWN
Platform: UNKNOWN
